cis_interface/.cis_metaschema.json
cis_interface/.cis_schema.yml
cis_interface/__init__.py
cis_interface/_version.py
cis_interface/backwards.py
cis_interface/command_line.py
cis_interface/config.py
cis_interface/defaults.cfg
cis_interface/getline_win32.h
cis_interface/platform.py
cis_interface/runner.py
cis_interface/scanf.py
cis_interface/schema.py
cis_interface/stdint.h
cis_interface/timing.py
cis_interface/tools.h
cis_interface/tools.py
cis_interface/units.py
cis_interface/yamlfile.py
cis_interface/communication/AsciiFileComm.h
cis_interface/communication/AsciiFileComm.py
cis_interface/communication/AsciiMapComm.py
cis_interface/communication/AsciiTableComm.h
cis_interface/communication/AsciiTableComm.py
cis_interface/communication/AsyncComm.py
cis_interface/communication/ClientComm.h
cis_interface/communication/ClientComm.py
cis_interface/communication/CommBase.h
cis_interface/communication/CommBase.py
cis_interface/communication/DefaultComm.h
cis_interface/communication/ErrorComm.py
cis_interface/communication/FileComm.py
cis_interface/communication/ForkComm.py
cis_interface/communication/IPCComm.h
cis_interface/communication/IPCComm.py
cis_interface/communication/JSONFileComm.py
cis_interface/communication/MatFileComm.py
cis_interface/communication/ObjFileComm.py
cis_interface/communication/PandasFileComm.py
cis_interface/communication/PickleFileComm.py
cis_interface/communication/PlyFileComm.py
cis_interface/communication/RMQAsyncComm.py
cis_interface/communication/RMQComm.py
cis_interface/communication/ServerComm.h
cis_interface/communication/ServerComm.py
cis_interface/communication/YAMLFileComm.py
cis_interface/communication/ZMQComm.h
cis_interface/communication/ZMQComm.py
cis_interface/communication/__init__.py
cis_interface/communication/comm_header.h
cis_interface/communication/communication.h
cis_interface/communication/tests/__init__.py
cis_interface/communication/tests/test_AsciiFileComm.py
cis_interface/communication/tests/test_AsciiMapComm.py
cis_interface-0.7.10.dist-info/LICENSE.txt
cis_interface-0.7.10.dist-info/METADATA
cis_interface-0.7.10.dist-info/WHEEL
cis_interface-0.7.10.dist-info/entry_points.txt
cis_interface-0.7.10.dist-info/top_level.txt
cis_interface-0.7.10.dist-info/RECORD
