Metadata-Version: 2.1
Name: cis-interface
Version: 0.7.10
Summary: A framework for combining interdependent models from multiple languages.
Home-page: https://github.com/cropsinsilico/cis_interface
Author: Meagan Lang
Author-email: langmm.astro@gmail.com
License: BSD
Download-URL: https://github.com/cropsinsilico/cis_interface/archive/0.7.10.tar.gz
Keywords: plants,simulation,models,framework
Platform: UNKNOWN
Classifier: Programming Language :: Python
Classifier: Programming Language :: C
Classifier: Programming Language :: C++
Classifier: Programming Language :: ML
Classifier: Operating System :: OS Independent
Classifier: Intended Audience :: Science/Research
Classifier: License :: OSI Approved :: BSD License
Classifier: Natural Language :: English
Classifier: Topic :: Scientific/Engineering
Classifier: Development Status :: 3 - Alpha
Requires-Dist: numpy (>=1.13.0)
Requires-Dist: scipy
Requires-Dist: pyyaml
Requires-Dist: pystache
Requires-Dist: pyzmq
Requires-Dist: psutil
Requires-Dist: jsonschema
Requires-Dist: perf
Requires-Dist: sysv-ipc ; platform_system != "Windows"
Requires-Dist: pandas ; python_version != "3.4"
Requires-Dist: matplotlib (<3.0) ; python_version < "3.5"
Requires-Dist: pint ; python_version == "2.7"
Requires-Dist: pandas (<0.21) ; python_version == "3.4"
Requires-Dist: python-rapidjson ; python_version >= "3.4"
Requires-Dist: unyt ; python_version >= "3.4"
Requires-Dist: matplotlib ; python_version >= "3.5"
